[
  {
    "page": "*",
    "position": "body",
    "method": "append",
    "label": "<div id='tcm-floating-wrapper' style='position: fixed; top: 10px; right: 10px; z-index: 999999;'><a id='tcm-top-btn' href='#' style='text-decoration: none !important; cursor: pointer !important; display: flex; align-items: center; justify-content: center;'><div style='width: 40px; height: 40px; background: linear-gradient(135deg, #495057 0%, #212529 100%); border: 2px solid #000; border-radius: 50%; display: flex; align-items: center; justify-content: center; box-shadow: 0 4px 8px rgba(0,0,0,0.5), inset 0 1px 1px rgba(255,255,255,0.2);'><svg width='22' height='22' viewBox='0 0 448 512' xmlns='http://www.w3.org/2000/svg'><path fill='white' d='M448 111.8C448 174.2 347.7 224 224 224S0 174.2 0 111.8C0 49.4 100.3 0 224 0S448 49.4 448 111.8zM0 190.4V240c0 62.4 100.3 112 224 112s224-49.6 224-112v-49.6c-44.7 35.1-125.2 58.4-224 58.4S44.7 225.5 0 190.4zM448 319.2V368c0 62.4-100.3 112-224 112S0 430.4 0 368v-48.8c44.7 35.1 125.2 58.4 224 58.4s179.3-23.3 224-58.4z'/></svg></div></a></div>",
    "containerStyle": "display:none; position:absolute; top: 45px; right: 0; z-index: 999999; background: linear-gradient(135deg, #212529 0%, #343a40 100%); border: 1px solid #111; padding: 5px 0; min-width: 180px; box-shadow: 0 10px 25px rgba(0,0,0,0.7); border-radius: 12px; overflow: hidden;",
    "itemStyle": "display:block; padding: 14px 20px; color: #fff !important; text-decoration: none !important; font-size: 14px; font-family: 'Segoe UI', sans-serif; border-bottom: 1px solid rgba(255,255,255,0.05);",
    "items": [
      { "label": "🔥 Rozpiski", "url": "https://twdatabase.online/AttackPlanner/Show" },
      { "label": "🛡️ Obstawy", "url": "https://twdatabase.online/Guards" },
      { "label": "⚔️ Kliny", "url": "https://twdatabase.online/Wedges" },
      { "label": "🗺️ Mapa", "url": "https://twdatabase.online/Map" }
    ]
  }
]
